phosphodisco/__init__.py
phosphodisco/annotation_association.py
phosphodisco/catheat.py
phosphodisco/classes.py
phosphodisco/cli.py
phosphodisco/constants.py
phosphodisco/datasets.py
phosphodisco/gene_ontology_analysis.py
phosphodisco/motif_analysis.py
phosphodisco/nominate_regulators.py
phosphodisco/parsers.py
phosphodisco/utils.py
phosphodisco/visualize.py
phosphodisco/data/GRCh38_latest_protein.faa
phosphodisco/data/config-custom_template0.yml
phosphodisco/data/config-custom_template1.yml
phosphodisco/data/config-custom_template2.yml
phosphodisco/data/interactions-Jan2021-dgidb.tsv
phosphodisco/data/kin_act_loops.csv
phosphodisco/data/kinase_list.tsv
phosphodisco/data/kinases_and_phosphatases.tsv
phosphodisco/data/protein_phosphatase_fromGeneNames_list.tsv
phosphodisco/data/ptm.sig.db.all.flanking.human.v1.9.0.gmt
phosphodisco/data/ptm.sig.db.all.flanking.mouse.v1.9.0.gmt
phosphodisco/data/ptm.sig.db.all.flanking.rat.v1.9.0.gmt
phosphodisco/tests/__init__.py
phosphodisco/tests/test_aa_overlap.py
phosphodisco/tests/test_classes.py
phosphodisco/tests/test_parsers.py
phosphodisco/tests/test_visualize.py
phosphodisco-0.0.2.dist-info/LICENSE
phosphodisco-0.0.2.dist-info/METADATA
phosphodisco-0.0.2.dist-info/WHEEL
phosphodisco-0.0.2.dist-info/entry_points.txt
phosphodisco-0.0.2.dist-info/top_level.txt
phosphodisco-0.0.2.dist-info/RECORD
