Metadata-Version: 2.1
Name: phosphodisco
Version: 0.0.2
Summary: A package for the discovery of co-regulated phosphorylation modules
Home-page: https://github.com/ruggleslab/phosphodisco
Author: Tobias Schraink, Ruggles Lab
Author-email: Tobias Schraink <tschraink@gmail.com>
License: MIT License        
Project-URL: Homepage, https://github.com/ruggleslab/phosphodisco
Project-URL: Bug Tracker, https://github.com/ruggleslab/phosphodisco/issues
Classifier: Programming Language :: Python :: 3
Classifier: License :: OSI Approved :: MIT License
Classifier: Operating System :: OS Independent
Requires-Python: >=3.8
License-File: LICENSE
Requires-Dist: pandas (>=0.24.2)
Requires-Dist: numpy (>=1.16.4)
Requires-Dist: scipy (>=1.2.1)
Requires-Dist: matplotlib (>=3.1.0)
Requires-Dist: seaborn (>=0.9.0)
Requires-Dist: scikit-learn (>=0.22.0)
Requires-Dist: statsmodels (>=0.11.0)
Requires-Dist: hypercluster (>=0.1.13)
Requires-Dist: oyaml (>=1.0)
Requires-Dist: logomaker (>=0.8)
Requires-Dist: snakemake (>=7.8.5)
Requires-Dist: hdbscan (>=0.8.28)
Requires-Dist: cython (>=0.29.30)
